peakipy/__init__.py
peakipy/constants.py
peakipy/fitting.py
peakipy/io.py
peakipy/lineshapes.py
peakipy/plotting.py
peakipy/utils.py
peakipy/cli/__init__.py
peakipy/cli/edit.py
peakipy/cli/main.py
peakipy-2.1.2.dist-info/METADATA
peakipy-2.1.2.dist-info/WHEEL
peakipy-2.1.2.dist-info/entry_points.txt
peakipy-2.1.2.dist-info/licenses/LICENSE
peakipy-2.1.2.dist-info/RECORD
