Metadata-Version: 2.4
Name: peakipy
Version: 2.1.2
Summary: Deconvolute overlapping NMR peaks
Author-email: j-brady <jacob.brady@protonmail.com>
License-Expression: MIT
License-File: LICENSE
Classifier: Intended Audience :: Science/Research
Classifier: Operating System :: MacOS :: MacOS X
Classifier: Operating System :: Microsoft :: Windows
Classifier: Operating System :: POSIX :: Linux
Classifier: Programming Language :: Python :: 3 :: Only
Classifier: Programming Language :: Python :: 3.11
Classifier: Topic :: Scientific/Engineering
Requires-Python: >=3.11
Requires-Dist: bokeh>=3.8.0
Requires-Dist: jedi>=0.19.2
Requires-Dist: jinja2>=3.1.6
Requires-Dist: lmfit>=1.3.4
Requires-Dist: matplotlib>=3.10.6
Requires-Dist: nmrglue>=0.11
Requires-Dist: numdifftools>=0.9.41
Requires-Dist: numpy>=2.3.3
Requires-Dist: pandas>=2.3.2
Requires-Dist: panel>=1.8.0
Requires-Dist: plotly>=6.3.0
Requires-Dist: plotpy>=2.7.5
Requires-Dist: pydantic>=2.11.9
Requires-Dist: pyyaml>=6.0.2
Requires-Dist: rich>=14.1.0
Requires-Dist: scikit-image>=0.25.2
Requires-Dist: scipy>=1.16.2
Requires-Dist: statsmodels>=0.14.5
Requires-Dist: tqdm>=4.67.1
Requires-Dist: typer>=0.17.4
